pfsspy/__init__.py
pfsspy/_version.py
pfsspy/analytic.py
pfsspy/coords.py
pfsspy/fieldline.py
pfsspy/grid.py
pfsspy/input.py
pfsspy/interpolator.py
pfsspy/map.py
pfsspy/output.py
pfsspy/pfss.py
pfsspy/sample_data.py
pfsspy/tracing.py
pfsspy/utils.py
pfsspy-1.2.0.dist-info/LICENSE
pfsspy-1.2.0.dist-info/METADATA
pfsspy-1.2.0.dist-info/WHEEL
pfsspy-1.2.0.dist-info/top_level.txt
pfsspy-1.2.0.dist-info/RECORD
