Metadata-Version: 2.1
Name: pfsspy
Version: 1.2.0
Summary: "Potential field source surface modelling"
Home-page: https://pfsspy.readthedocs.io/en/stable/
Author: David Stansby
Author-email: dstansby@gmail.com
License: GPLv3
Keywords: solar physics,solar,science,sun
Platform: any
Classifier: Development Status :: 6 - Mature
Classifier: Intended Audience :: Science/Research
Classifier: License :: OSI Approved :: GNU General Public License v3 (GPLv3)
Classifier: Natural Language :: English
Classifier: Operating System :: OS Independent
Classifier: Programming Language :: Python
Classifier: Programming Language :: Python :: 3
Classifier: Programming Language :: Python :: 3.9
Classifier: Programming Language :: Python :: 3.10
Classifier: Programming Language :: Python :: 3.11
Classifier: Topic :: Scientific/Engineering :: Physics
Provides: pfsspy
Requires-Python: >=3.9
License-File: LICENSE
Requires-Dist: astropy (>=5.0)
Requires-Dist: numpy
Requires-Dist: scikit-image
Requires-Dist: scipy
Requires-Dist: sunpy[map] (>=4)
Provides-Extra: analytic
Requires-Dist: sympy ; extra == 'analytic'
Provides-Extra: docs
Requires-Dist: graphviz ; extra == 'docs'
Requires-Dist: importlib-metadata ; extra == 'docs'
Requires-Dist: pillow ; extra == 'docs'
Requires-Dist: reproject ; extra == 'docs'
Requires-Dist: sphinx (>2) ; extra == 'docs'
Requires-Dist: sphinx-automodapi (>=0.10) ; extra == 'docs'
Requires-Dist: sphinx-gallery ; extra == 'docs'
Requires-Dist: sphinx-rtd-theme ; extra == 'docs'
Requires-Dist: streamtracer ; extra == 'docs'
Requires-Dist: sunpy[map,net] ; extra == 'docs'
Requires-Dist: sympy ; extra == 'docs'
Provides-Extra: performance
Requires-Dist: numba ; extra == 'performance'
Requires-Dist: streamtracer ; extra == 'performance'
Provides-Extra: test
Requires-Dist: numpy ; extra == 'test'
Requires-Dist: parfive ; extra == 'test'
Requires-Dist: pytest ; extra == 'test'
Requires-Dist: pytest-cov ; extra == 'test'
Requires-Dist: reproject ; extra == 'test'
Requires-Dist: streamtracer ; extra == 'test'
Requires-Dist: sympy ; extra == 'test'
